dti_tax_core_vsdc_api_client_swagger/__init__.py
dti_tax_core_vsdc_api_client_swagger/api_client.py
dti_tax_core_vsdc_api_client_swagger/configuration.py
dti_tax_core_vsdc_api_client_swagger/rest.py
dti_tax_core_vsdc_api_client_swagger/api/__init__.py
dti_tax_core_vsdc_api_client_swagger/api/invoices_api.py
dti_tax_core_vsdc_api_client_swagger/api/status_api.py
dti_tax_core_vsdc_api_client_swagger/models/__init__.py
dti_tax_core_vsdc_api_client_swagger/models/get_status_response.py
dti_tax_core_vsdc_api_client_swagger/models/invoice_request.py
dti_tax_core_vsdc_api_client_swagger/models/invoice_result.py
dti_tax_core_vsdc_api_client_swagger/models/item.py
dti_tax_core_vsdc_api_client_swagger/models/payment.py
dti_tax_core_vsdc_api_client_swagger/models/tax_category.py
dti_tax_core_vsdc_api_client_swagger/models/tax_core_public_configuration.py
dti_tax_core_vsdc_api_client_swagger/models/tax_item.py
dti_tax_core_vsdc_api_client_swagger/models/tax_rate.py
dti_tax_core_vsdc_api_client_swagger/models/tax_rate_group.py
test/__init__.py
test/test_get_status_response.py
test/test_invoice_request.py
test/test_invoice_result.py
test/test_invoices_api.py
test/test_item.py
test/test_payment.py
test/test_status_api.py
test/test_tax_category.py
test/test_tax_core_public_configuration.py
test/test_tax_item.py
test/test_tax_rate.py
test/test_tax_rate_group.py
dti_tax_core_vsdc_api_client_swagger-1.0.0.dist-info/METADATA
dti_tax_core_vsdc_api_client_swagger-1.0.0.dist-info/WHEEL
dti_tax_core_vsdc_api_client_swagger-1.0.0.dist-info/top_level.txt
dti_tax_core_vsdc_api_client_swagger-1.0.0.dist-info/RECORD
