Metadata-Version: 2.1
Name: dti-tax-core-vsdc-api-client-swagger
Version: 1.0.0
Summary: Dti.TaxCore.VSDC.Api
Home-page: https://github.com/modoolar/dti_tax_core_vsdc_api_client_swagger
Author: agajic-modoolar
Author-email: aleksandar.gajic@modoolar.com
License: MIT
Keywords: Swagger,Dti.TaxCore.VSDC.Api
Platform: UNKNOWN
Requires-Dist: certifi (>=2017.4.17)
Requires-Dist: python-dateutil (>=2.1)
Requires-Dist: six (>=1.10)
Requires-Dist: urllib3 (>=1.23)
